{
  "generated_at_utc": "2026-06-01T23:43:51.560980+00:00",
  "source": "yfinance",
  "interval": "1d",
  "lookback": "400d",
  "trading_days": 252,
  "count": 86,
  "data": [
    {
      "symbol": "ABEV3.SA",
      "name": "Ambev",
      "price": 16.43,
      "vol_annual": 0.25697415
    },
    {
      "symbol": "ALOS3.SA",
      "name": "Allos",
      "price": 27.780001,
      "vol_annual": 0.2505988
    },
    {
      "symbol": "ASAI3.SA",
      "name": "Assaí",
      "price": 8.6,
      "vol_annual": 0.48321158
    },
    {
      "symbol": "AURE3.SA",
      "name": "Auren Energia",
      "price": 12.06,
      "vol_annual": 0.31771444
    },
    {
      "symbol": "AXIA3.SA",
      "name": "Axia (Verificar Ticker)",
      "price": 51.150002,
      "vol_annual": 0.33965835
    },
    {
      "symbol": "AXIA6.SA",
      "name": "Axia (Verificar Ticker)",
      "price": 56.200001,
      "vol_annual": 0.27143838
    },
    {
      "symbol": "AXIA7.SA",
      "name": "Axia (Verificar Ticker)",
      "price": 49.400002,
      "vol_annual": 0.37155847
    },
    {
      "symbol": "AZZA3.SA",
      "name": "Azzas 2154 (Arezzo+Soma)",
      "price": 18.780001,
      "vol_annual": 0.49082366
    },
    {
      "symbol": "B3SA3.SA",
      "name": "B3",
      "price": 16.25,
      "vol_annual": 0.35280669
    },
    {
      "symbol": "BBAS3.SA",
      "name": "Banco do Brasil",
      "price": 20.08,
      "vol_annual": 0.28253513
    },
    {
      "symbol": "BBDC3.SA",
      "name": "Bradesco (ON)",
      "price": 15.29,
      "vol_annual": 0.25814213
    },
    {
      "symbol": "BBDC4.SA",
      "name": "Bradesco (PN)",
      "price": 17.5,
      "vol_annual": 0.28164339
    },
    {
      "symbol": "BBSE3.SA",
      "name": "BB Seguridade",
      "price": 35.029999,
      "vol_annual": 0.22076436
    },
    {
      "symbol": "BEEF3.SA",
      "name": "Minerva",
      "price": 3.5,
      "vol_annual": 0.48286944
    },
    {
      "symbol": "BOVA11.SA",
      "name": "iShares Ibovespa",
      "price": 169.119995,
      "vol_annual": 0.17268139
    },
    {
      "symbol": "BPAC11.SA",
      "name": "BTG Pactual",
      "price": 52.75,
      "vol_annual": 0.31796809
    },
    {
      "symbol": "BRAP4.SA",
      "name": "Bradespar",
      "price": 22.870001,
      "vol_annual": 0.25684921
    },
    {
      "symbol": "BRAV3.SA",
      "name": "Brava Energia (3R + Enauta)",
      "price": 20.77,
      "vol_annual": 0.46304399
    },
    {
      "symbol": "BRKM5.SA",
      "name": "Braskem",
      "price": 10.23,
      "vol_annual": 0.63034606
    },
    {
      "symbol": "CEAB3.SA",
      "name": "C&A",
      "price": 11.33,
      "vol_annual": 0.56820345
    },
    {
      "symbol": "CMIG4.SA",
      "name": "Cemig",
      "price": 10.81,
      "vol_annual": 0.24229569
    },
    {
      "symbol": "CMIN3.SA",
      "name": "CSN Mineração",
      "price": 4.54,
      "vol_annual": 0.37113686
    },
    {
      "symbol": "COGN3.SA",
      "name": "Cogna",
      "price": 2.47,
      "vol_annual": 0.50958164
    },
    {
      "symbol": "CPFE3.SA",
      "name": "CPFL Energia",
      "price": 42.849998,
      "vol_annual": 0.22813668
    },
    {
      "symbol": "CPLE3.SA",
      "name": "Copel",
      "price": 14.41,
      "vol_annual": 0.25304133
    },
    {
      "symbol": "CSAN3.SA",
      "name": "Cosan",
      "price": 3.88,
      "vol_annual": 0.48677298
    },
    {
      "symbol": "CSMG3.SA",
      "name": "Copasa",
      "price": 52.200001,
      "vol_annual": 0.29952072
    },
    {
      "symbol": "CSNA3.SA",
      "name": "CSN Siderúrgica",
      "price": 6.55,
      "vol_annual": 0.49586501
    },
    {
      "symbol": "CURY3.SA",
      "name": "Cury Construtora",
      "price": 31.32,
      "vol_annual": 0.35375126
    },
    {
      "symbol": "CXSE3.SA",
      "name": "Caixa Seguridade",
      "price": 17.450001,
      "vol_annual": 0.23635845
    },
    {
      "symbol": "CYRE3.SA",
      "name": "Cyrela",
      "price": 22.379999,
      "vol_annual": 0.41184464
    },
    {
      "symbol": "CYRE4.SA",
      "name": "Cyrela (PN)",
      "price": 20.43,
      "vol_annual": 0.51978257
    },
    {
      "symbol": "DIRR3.SA",
      "name": "Direcional",
      "price": 13.37,
      "vol_annual": 0.38347673
    },
    {
      "symbol": "EGIE3.SA",
      "name": "Engie Brasil",
      "price": 32.799999,
      "vol_annual": 0.23699351
    },
    {
      "symbol": "EMBJ3.SA",
      "name": "Embraer (Verificar: EMBR3)",
      "price": 72.169998,
      "vol_annual": 0.41540357
    },
    {
      "symbol": "ENEV3.SA",
      "name": "Eneva",
      "price": 24.879999,
      "vol_annual": 0.32664027
    },
    {
      "symbol": "ENGI11.SA",
      "name": "Energisa",
      "price": 47.919998,
      "vol_annual": 0.27355839
    },
    {
      "symbol": "EQTL3.SA",
      "name": "Equatorial",
      "price": 38.43,
      "vol_annual": 0.25150897
    },
    {
      "symbol": "FLRY3.SA",
      "name": "Fleury",
      "price": 15.31,
      "vol_annual": 0.3008478
    },
    {
      "symbol": "GGBR4.SA",
      "name": "Gerdau",
      "price": 23.139999,
      "vol_annual": 0.28751624
    },
    {
      "symbol": "GOAU4.SA",
      "name": "Metalúrgica Gerdau",
      "price": 9.99,
      "vol_annual": 0.29272259
    },
    {
      "symbol": "HAPV3.SA",
      "name": "Hapvida",
      "price": 12.2,
      "vol_annual": 0.70521886
    },
    {
      "symbol": "HYPE3.SA",
      "name": "Hypera Pharma",
      "price": 21.43,
      "vol_annual": 0.33688542
    },
    {
      "symbol": "IGTI11.SA",
      "name": "Iguatemi",
      "price": 25.67,
      "vol_annual": 0.28584355
    },
    {
      "symbol": "IRBR3.SA",
      "name": "IRB Re",
      "price": 51.360001,
      "vol_annual": 0.42375734
    },
    {
      "symbol": "ISAE4.SA",
      "name": "ISA CTEEP (TRPL4)",
      "price": 26.860001,
      "vol_annual": 0.21319799
    },
    {
      "symbol": "ITSA4.SA",
      "name": "Itaúsa",
      "price": 12.76,
      "vol_annual": 0.24517261
    },
    {
      "symbol": "ITUB4.SA",
      "name": "Itaú Unibanco",
      "price": 39.360001,
      "vol_annual": 0.23568305
    },
    {
      "symbol": "KLBN11.SA",
      "name": "Klabin",
      "price": 16.639999,
      "vol_annual": 0.21982317
    },
    {
      "symbol": "LREN3.SA",
      "name": "Lojas Renner",
      "price": 15.02,
      "vol_annual": 0.42381637
    },
    {
      "symbol": "MBRF3.SA",
      "name": "Marfrig (Verificar: MRFG3)",
      "price": 15.83,
      "vol_annual": 0.55971145
    },
    {
      "symbol": "MGLU3.SA",
      "name": "Magazine Luiza",
      "price": 5.82,
      "vol_annual": 0.63142795
    },
    {
      "symbol": "MOTV3.SA",
      "name": "Movida (Verificar: MOVI3)",
      "price": 14.13,
      "vol_annual": 0.27584781
    },
    {
      "symbol": "MRVE3.SA",
      "name": "MRV",
      "price": 5.72,
      "vol_annual": 0.49832215
    },
    {
      "symbol": "MULT3.SA",
      "name": "Multiplan",
      "price": 29.299999,
      "vol_annual": 0.2639409
    },
    {
      "symbol": "NATU3.SA",
      "name": "Natura",
      "price": 9.84,
      "vol_annual": 1.42153327
    },
    {
      "symbol": "PCAR3.SA",
      "name": "Pão de Açúcar",
      "price": 1.61,
      "vol_annual": 0.67514303
    },
    {
      "symbol": "PETR3.SA",
      "name": "Petrobras (ON)",
      "price": 47.34,
      "vol_annual": 0.28358901
    },
    {
      "symbol": "PETR4.SA",
      "name": "Petrobras (PN)",
      "price": 42.369999,
      "vol_annual": 0.25167876
    },
    {
      "symbol": "POMO4.SA",
      "name": "Marcopolo",
      "price": 6.12,
      "vol_annual": 0.3859836
    },
    {
      "symbol": "PRIO3.SA",
      "name": "Prio (PetroRio)",
      "price": 62.82,
      "vol_annual": 0.3451432
    },
    {
      "symbol": "PSSA3.SA",
      "name": "Porto Seguro",
      "price": 48.0,
      "vol_annual": 0.25196657
    },
    {
      "symbol": "RADL3.SA",
      "name": "Raia Drogasil",
      "price": 17.860001,
      "vol_annual": 0.41047999
    },
    {
      "symbol": "RAIL3.SA",
      "name": "Rumo",
      "price": 13.92,
      "vol_annual": 0.34035926
    },
    {
      "symbol": "RAIZ4.SA",
      "name": "Raízen",
      "price": 0.4,
      "vol_annual": 0.63376606
    },
    {
      "symbol": "RDOR3.SA",
      "name": "Rede D'Or",
      "price": 33.869999,
      "vol_annual": 0.30564808
    },
    {
      "symbol": "RECV3.SA",
      "name": "PetroReconcavo",
      "price": 11.22,
      "vol_annual": 0.35250395
    },
    {
      "symbol": "RENT3.SA",
      "name": "Localiza",
      "price": 41.34,
      "vol_annual": 0.40879966
    },
    {
      "symbol": "RENT4.SA",
      "name": "Localiza (PN - Antiga)",
      "price": 40.18,
      "vol_annual": 0.47589494
    },
    {
      "symbol": "SANB11.SA",
      "name": "Santander Brasil",
      "price": 27.209999,
      "vol_annual": 0.2805471
    },
    {
      "symbol": "SBSP3.SA",
      "name": "Sabesp",
      "price": 27.280001,
      "vol_annual": 0.25997817
    },
    {
      "symbol": "SLCE3.SA",
      "name": "SLC Agrícola",
      "price": 15.21,
      "vol_annual": 0.2368142
    },
    {
      "symbol": "SMFT3.SA",
      "name": "Smart Fit",
      "price": 18.35,
      "vol_annual": 0.35931249
    },
    {
      "symbol": "SUZB3.SA",
      "name": "Suzano",
      "price": 40.650002,
      "vol_annual": 0.24831441
    },
    {
      "symbol": "TAEE11.SA",
      "name": "Taesa",
      "price": 38.900002,
      "vol_annual": 0.19961389
    },
    {
      "symbol": "TIMS3.SA",
      "name": "TIM",
      "price": 21.780001,
      "vol_annual": 0.29014256
    },
    {
      "symbol": "TOTS3.SA",
      "name": "Totvs",
      "price": 34.5,
      "vol_annual": 0.34496145
    },
    {
      "symbol": "UGPA3.SA",
      "name": "Ultrapar",
      "price": 25.41,
      "vol_annual": 0.34247074
    },
    {
      "symbol": "USIM5.SA",
      "name": "Usiminas",
      "price": 11.09,
      "vol_annual": 0.42199823
    },
    {
      "symbol": "VALE3.SA",
      "name": "Vale",
      "price": 81.699997,
      "vol_annual": 0.26139569
    },
    {
      "symbol": "VAMO3.SA",
      "name": "Vamos",
      "price": 3.0,
      "vol_annual": 0.61211049
    },
    {
      "symbol": "VBBR3.SA",
      "name": "Vibra (BR Distribuidora)",
      "price": 29.91,
      "vol_annual": 0.30499139
    },
    {
      "symbol": "VIVA3.SA",
      "name": "Vivara",
      "price": 21.549999,
      "vol_annual": 0.39690982
    },
    {
      "symbol": "VIVT3.SA",
      "name": "Vivo",
      "price": 33.25,
      "vol_annual": 0.25592539
    },
    {
      "symbol": "WEGE3.SA",
      "name": "WEG",
      "price": 43.0,
      "vol_annual": 0.30709118
    },
    {
      "symbol": "YDUQ3.SA",
      "name": "Yduqs (Estácio)",
      "price": 9.46,
      "vol_annual": 0.50612638
    }
  ]
}