{
  "generated_at_utc": "2026-04-22T07:51:55.120505+00:00",
  "source": "yfinance",
  "interval": "1d",
  "lookback": "400d",
  "trading_days": 252,
  "count": 85,
  "data": [
    {
      "symbol": "ABEV3.SA",
      "name": "Ambev",
      "price": 15.31,
      "vol_annual": 0.2290221
    },
    {
      "symbol": "ALOS3.SA",
      "name": "Allos",
      "price": 33.5,
      "vol_annual": 0.24274976
    },
    {
      "symbol": "ASAI3.SA",
      "name": "Assaí",
      "price": 9.55,
      "vol_annual": 0.4920279
    },
    {
      "symbol": "AURE3.SA",
      "name": "Auren Energia",
      "price": 14.61,
      "vol_annual": 0.31273393
    },
    {
      "symbol": "AXIA3.SA",
      "name": "Axia (Verificar Ticker)",
      "price": 63.93,
      "vol_annual": 0.33322789
    },
    {
      "symbol": "AXIA6.SA",
      "name": "Axia (Verificar Ticker)",
      "price": 70.089996,
      "vol_annual": 0.26003855
    },
    {
      "symbol": "AXIA7.SA",
      "name": "Axia (Verificar Ticker)",
      "price": 61.200001,
      "vol_annual": 0.38127986
    },
    {
      "symbol": "AZZA3.SA",
      "name": "Azzas 2154 (Arezzo+Soma)",
      "price": 21.870001,
      "vol_annual": 0.48144118
    },
    {
      "symbol": "B3SA3.SA",
      "name": "B3",
      "price": 19.25,
      "vol_annual": 0.34651219
    },
    {
      "symbol": "BBAS3.SA",
      "name": "Banco do Brasil",
      "price": 24.280001,
      "vol_annual": 0.27467729
    },
    {
      "symbol": "BBDC3.SA",
      "name": "Bradesco (ON)",
      "price": 18.059999,
      "vol_annual": 0.25594105
    },
    {
      "symbol": "BBDC4.SA",
      "name": "Bradesco (PN)",
      "price": 21.030001,
      "vol_annual": 0.27778996
    },
    {
      "symbol": "BBSE3.SA",
      "name": "BB Seguridade",
      "price": 35.279999,
      "vol_annual": 0.21839093
    },
    {
      "symbol": "BEEF3.SA",
      "name": "Minerva",
      "price": 4.13,
      "vol_annual": 0.46626658
    },
    {
      "symbol": "BPAC11.SA",
      "name": "BTG Pactual",
      "price": 64.129997,
      "vol_annual": 0.31334578
    },
    {
      "symbol": "BRAP4.SA",
      "name": "Bradespar",
      "price": 25.18,
      "vol_annual": 0.25949002
    },
    {
      "symbol": "BRAV3.SA",
      "name": "Brava Energia (3R + Enauta)",
      "price": 20.4,
      "vol_annual": 0.48329616
    },
    {
      "symbol": "BRKM5.SA",
      "name": "Braskem",
      "price": 8.98,
      "vol_annual": 0.59148388
    },
    {
      "symbol": "CEAB3.SA",
      "name": "C&A",
      "price": 12.98,
      "vol_annual": 0.55837827
    },
    {
      "symbol": "CMIG4.SA",
      "name": "Cemig",
      "price": 13.73,
      "vol_annual": 0.23396096
    },
    {
      "symbol": "CMIN3.SA",
      "name": "CSN Mineração",
      "price": 5.04,
      "vol_annual": 0.38474589
    },
    {
      "symbol": "COGN3.SA",
      "name": "Cogna",
      "price": 3.3,
      "vol_annual": 0.52243134
    },
    {
      "symbol": "CPFE3.SA",
      "name": "CPFL Energia",
      "price": 55.419998,
      "vol_annual": 0.21586387
    },
    {
      "symbol": "CPLE3.SA",
      "name": "Copel",
      "price": 16.9,
      "vol_annual": 0.24904166
    },
    {
      "symbol": "CSAN3.SA",
      "name": "Cosan",
      "price": 5.3,
      "vol_annual": 0.47684667
    },
    {
      "symbol": "CSMG3.SA",
      "name": "Copasa",
      "price": 58.029999,
      "vol_annual": 0.29307154
    },
    {
      "symbol": "CSNA3.SA",
      "name": "CSN Siderúrgica",
      "price": 6.82,
      "vol_annual": 0.49802726
    },
    {
      "symbol": "CURY3.SA",
      "name": "Cury Construtora",
      "price": 34.57,
      "vol_annual": 0.33512392
    },
    {
      "symbol": "CXSE3.SA",
      "name": "Caixa Seguridade",
      "price": 19.030001,
      "vol_annual": 0.23349577
    },
    {
      "symbol": "CYRE3.SA",
      "name": "Cyrela",
      "price": 27.77,
      "vol_annual": 0.40436733
    },
    {
      "symbol": "CYRE4.SA",
      "name": "Cyrela (PN)",
      "price": 25.299999,
      "vol_annual": 0.51409572
    },
    {
      "symbol": "DIRR3.SA",
      "name": "Direcional",
      "price": 14.9,
      "vol_annual": 0.36970008
    },
    {
      "symbol": "EGIE3.SA",
      "name": "Engie Brasil",
      "price": 37.419998,
      "vol_annual": 0.23130373
    },
    {
      "symbol": "EMBJ3.SA",
      "name": "Embraer (Verificar: EMBR3)",
      "price": 84.790001,
      "vol_annual": 0.39196138
    },
    {
      "symbol": "ENEV3.SA",
      "name": "Eneva",
      "price": 27.290001,
      "vol_annual": 0.31986885
    },
    {
      "symbol": "ENGI11.SA",
      "name": "Energisa",
      "price": 57.470001,
      "vol_annual": 0.26799573
    },
    {
      "symbol": "EQTL3.SA",
      "name": "Equatorial",
      "price": 45.060001,
      "vol_annual": 0.24379339
    },
    {
      "symbol": "FLRY3.SA",
      "name": "Fleury",
      "price": 16.68,
      "vol_annual": 0.29679497
    },
    {
      "symbol": "GGBR4.SA",
      "name": "Gerdau",
      "price": 21.440001,
      "vol_annual": 0.28676992
    },
    {
      "symbol": "GOAU4.SA",
      "name": "Metalúrgica Gerdau",
      "price": 9.45,
      "vol_annual": 0.29115479
    },
    {
      "symbol": "HAPV3.SA",
      "name": "Hapvida",
      "price": 12.38,
      "vol_annual": 0.68431849
    },
    {
      "symbol": "HYPE3.SA",
      "name": "Hypera Pharma",
      "price": 23.49,
      "vol_annual": 0.33587895
    },
    {
      "symbol": "IGTI11.SA",
      "name": "Iguatemi",
      "price": 30.059999,
      "vol_annual": 0.28068906
    },
    {
      "symbol": "IRBR3.SA",
      "name": "IRB Re",
      "price": 58.299999,
      "vol_annual": 0.42167097
    },
    {
      "symbol": "ISAE4.SA",
      "name": "ISA CTEEP (TRPL4)",
      "price": 30.83,
      "vol_annual": 0.20779899
    },
    {
      "symbol": "ITSA4.SA",
      "name": "Itaúsa",
      "price": 14.74,
      "vol_annual": 0.23944388
    },
    {
      "symbol": "ITUB4.SA",
      "name": "Itaú Unibanco",
      "price": 46.369999,
      "vol_annual": 0.22961644
    },
    {
      "symbol": "KLBN11.SA",
      "name": "Klabin",
      "price": 18.76,
      "vol_annual": 0.21891145
    },
    {
      "symbol": "LREN3.SA",
      "name": "Lojas Renner",
      "price": 15.15,
      "vol_annual": 0.41682894
    },
    {
      "symbol": "MBRF3.SA",
      "name": "Marfrig (Verificar: MRFG3)",
      "price": 19.57,
      "vol_annual": 0.55763421
    },
    {
      "symbol": "MGLU3.SA",
      "name": "Magazine Luiza",
      "price": 9.35,
      "vol_annual": 0.62468094
    },
    {
      "symbol": "MOTV3.SA",
      "name": "Movida (Verificar: MOVI3)",
      "price": 17.450001,
      "vol_annual": 0.27006931
    },
    {
      "symbol": "MRVE3.SA",
      "name": "MRV",
      "price": 7.67,
      "vol_annual": 0.49122267
    },
    {
      "symbol": "MULT3.SA",
      "name": "Multiplan",
      "price": 34.43,
      "vol_annual": 0.25479905
    },
    {
      "symbol": "NATU3.SA",
      "name": "Natura",
      "price": 10.18,
      "vol_annual": 1.51075635
    },
    {
      "symbol": "PCAR3.SA",
      "name": "Pão de Açúcar",
      "price": 2.59,
      "vol_annual": 0.65554441
    },
    {
      "symbol": "PETR3.SA",
      "name": "Petrobras (ON)",
      "price": 51.740002,
      "vol_annual": 0.2771038
    },
    {
      "symbol": "PETR4.SA",
      "name": "Petrobras (PN)",
      "price": 47.02,
      "vol_annual": 0.24712872
    },
    {
      "symbol": "POMO4.SA",
      "name": "Marcopolo",
      "price": 7.1,
      "vol_annual": 0.38417909
    },
    {
      "symbol": "PRIO3.SA",
      "name": "Prio (PetroRio)",
      "price": 61.630001,
      "vol_annual": 0.34164613
    },
    {
      "symbol": "PSSA3.SA",
      "name": "Porto Seguro",
      "price": 55.41,
      "vol_annual": 0.24327714
    },
    {
      "symbol": "RADL3.SA",
      "name": "Raia Drogasil",
      "price": 23.360001,
      "vol_annual": 0.40063106
    },
    {
      "symbol": "RAIL3.SA",
      "name": "Rumo",
      "price": 16.469999,
      "vol_annual": 0.33217737
    },
    {
      "symbol": "RAIZ4.SA",
      "name": "Raízen",
      "price": 0.54,
      "vol_annual": 0.58957705
    },
    {
      "symbol": "RDOR3.SA",
      "name": "Rede D'Or",
      "price": 39.439999,
      "vol_annual": 0.29388241
    },
    {
      "symbol": "RECV3.SA",
      "name": "PetroReconcavo",
      "price": 13.1,
      "vol_annual": 0.34567742
    },
    {
      "symbol": "RENT3.SA",
      "name": "Localiza",
      "price": 51.98,
      "vol_annual": 0.39424267
    },
    {
      "symbol": "RENT4.SA",
      "name": "Localiza (PN - Antiga)",
      "price": 50.139999,
      "vol_annual": 0.45565648
    },
    {
      "symbol": "SANB11.SA",
      "name": "Santander Brasil",
      "price": 31.6,
      "vol_annual": 0.27458367
    },
    {
      "symbol": "SBSP3.SA",
      "name": "Sabesp",
      "price": 176.039993,
      "vol_annual": 0.25350914
    },
    {
      "symbol": "SLCE3.SA",
      "name": "SLC Agrícola",
      "price": 17.85,
      "vol_annual": 0.23945233
    },
    {
      "symbol": "SMFT3.SA",
      "name": "Smart Fit",
      "price": 18.82,
      "vol_annual": 0.34290791
    },
    {
      "symbol": "SUZB3.SA",
      "name": "Suzano",
      "price": 47.799999,
      "vol_annual": 0.24678785
    },
    {
      "symbol": "TAEE11.SA",
      "name": "Taesa",
      "price": 45.860001,
      "vol_annual": 0.19011783
    },
    {
      "symbol": "TIMS3.SA",
      "name": "TIM",
      "price": 26.85,
      "vol_annual": 0.27457286
    },
    {
      "symbol": "TOTS3.SA",
      "name": "Totvs",
      "price": 34.869999,
      "vol_annual": 0.32647575
    },
    {
      "symbol": "UGPA3.SA",
      "name": "Ultrapar",
      "price": 29.870001,
      "vol_annual": 0.33984984
    },
    {
      "symbol": "USIM5.SA",
      "name": "Usiminas",
      "price": 7.27,
      "vol_annual": 0.41056186
    },
    {
      "symbol": "VALE3.SA",
      "name": "Vale",
      "price": 88.730003,
      "vol_annual": 0.26099102
    },
    {
      "symbol": "VAMO3.SA",
      "name": "Vamos",
      "price": 4.57,
      "vol_annual": 0.60601442
    },
    {
      "symbol": "VBBR3.SA",
      "name": "Vibra (BR Distribuidora)",
      "price": 33.360001,
      "vol_annual": 0.30131976
    },
    {
      "symbol": "VIVA3.SA",
      "name": "Vivara",
      "price": 27.51,
      "vol_annual": 0.38167817
    },
    {
      "symbol": "VIVT3.SA",
      "name": "Vivo",
      "price": 41.009998,
      "vol_annual": 0.24307044
    },
    {
      "symbol": "WEGE3.SA",
      "name": "WEG",
      "price": 48.48,
      "vol_annual": 0.30088646
    },
    {
      "symbol": "YDUQ3.SA",
      "name": "Yduqs (Estácio)",
      "price": 11.79,
      "vol_annual": 0.51705706
    }
  ]
}